LICENCE
README.md
setup.py
agent/__init__.py
agent/core/__init__.py
agent/core/agent.py
agent/core/analyzer.py
agent/core/exceptions.py
agent/core/executor.py
agent/core/registry.py
agent/core/responder.py
agent/core/utils.py
agent/integrations/__init__.py
agent/integrations/llm_base.py
agent/integrations/llm_gemini.py
agent/integrations/llm_grok.py
agent/integrations/llm_groq.py
agent/integrations/llm_llama.py
agent/integrations/llm_ollama.py
agent/integrations/llm_openai.py
smartagent_sf.egg-info/PKG-INFO
smartagent_sf.egg-info/SOURCES.txt
smartagent_sf.egg-info/dependency_links.txt
smartagent_sf.egg-info/requires.txt
smartagent_sf.egg-info/top_level.txt