Metadata-Version: 2.4
Name: smartagent-sf
Version: 0.1.3
Summary: Biblioteca Python para criar agentes de IA com execução determinística
Home-page: https://github.com/lhabacuc/smartagent
Author: Liedson Habacuc
Author-email: lisvaldosf@gmail.com
License: MIT
Classifier: Development Status :: 3 - Alpha
Classifier: Intended Audience :: Developers
Classifier: Topic :: Software Development :: Libraries :: Python Modules
Classifier: License :: OSI Approved :: MIT License
Classifier: Programming Language :: Python :: 3
Classifier: Programming Language :: Python :: 3.8
Classifier: Programming Language :: Python :: 3.9
Classifier: Programming Language :: Python :: 3.10
Classifier: Programming Language :: Python :: 3.11
Requires-Python: >=3.8
License-File: LICENCE
Requires-Dist: requests>=2.25.0
Provides-Extra: dev
Requires-Dist: groq; extra == "dev"
Requires-Dist: openai; extra == "dev"
Requires-Dist: google-generativeai; extra == "dev"
Requires-Dist: ollama; extra == "dev"
Requires-Dist: llama-cpp-python; extra == "dev"
Requires-Dist: pytest; extra == "dev"
Requires-Dist: pytest-mock; extra == "dev"
Requires-Dist: black; extra == "dev"
Requires-Dist: flake8; extra == "dev"
Requires-Dist: mypy; extra == "dev"
Requires-Dist: isort; extra == "dev"
Requires-Dist: requests; extra == "dev"
Dynamic: author
Dynamic: author-email
Dynamic: classifier
Dynamic: description
Dynamic: description-content-type
Dynamic: home-page
Dynamic: license
Dynamic: license-file
Dynamic: provides-extra
Dynamic: requires-dist
Dynamic: requires-python
Dynamic: summary
